kostalplenticore.py
kostalplenticore-0.1.dist-info/LICENSE
kostalplenticore-0.1.dist-info/METADATA
kostalplenticore-0.1.dist-info/WHEEL
kostalplenticore-0.1.dist-info/top_level.txt
kostalplenticore-0.1.dist-info/RECORD
