Metadata-Version: 2.1
Name: kostalplenticore
Version: 0.1
Summary: API call to Kostal Plenticore
Home-page: https://github.com/ITTV-tools/kostalplenticorepy
Author: ittv-tools
Author-email: UNKNOWN
License: UNKNOWN
Platform: UNKNOWN
